server.py
helmfile_mcp_server-0.1.0.dist-info/METADATA
helmfile_mcp_server-0.1.0.dist-info/WHEEL
helmfile_mcp_server-0.1.0.dist-info/top_level.txt
helmfile_mcp_server-0.1.0.dist-info/RECORD
