Metadata-Version: 2.4
Name: helmfile-mcp-server
Version: 0.1.0
Summary: A FastMCP server for Helmfile operations
Author-email: Your Name <your.email@example.com>
Requires-Python: >=3.11
Requires-Dist: fastmcp>=0.1.0
Requires-Dist: pydantic>=2.0.0
